flats_crawling_tools/__init__.py
flats_crawling_tools/ScrappersMothers/RentScrapperMother.py
flats_crawling_tools/ScrappersMothers/__init__.py
flats_crawling_tools-0.0.1.dist-info/METADATA
flats_crawling_tools-0.0.1.dist-info/WHEEL
flats_crawling_tools-0.0.1.dist-info/top_level.txt
flats_crawling_tools-0.0.1.dist-info/RECORD
