Metadata-Version: 2.1
Name: flats-crawling-tools
Version: 0.0.1
Summary: some basic tools for crawling flats data
Home-page: UNKNOWN
Author: Mohamed Amjad LASRI
Author-email: amjadepot@gmail.com
License: MIT
Download-URL: https://pypi.org/project/flats_crawling_tools
Keywords: crawling
Platform: UNKNOWN
